etch_a_tv/__main__.py
etch_a_tv/modem.py
etch_a_tv/rigctl.py
etch_a_tv-0.1.1.dist-info/entry_points.txt
etch_a_tv-0.1.1.dist-info/WHEEL
etch_a_tv-0.1.1.dist-info/METADATA
etch_a_tv-0.1.1.dist-info/RECORD
